{"patterns": {"test_pattern_0": {"type": "test_pattern", "features": {"type": "success", "duration": 1.6, "resources": {"cpu": 55.0, "memory": 520.0}, "context": {"goal_id": "test_goal", "plugin_id": "test_plugin"}}, "success_rate": 1.0, "frequency": 2, "last_seen": "2025-05-06T18:40:41.479021", "related_patterns": []}, "test_pattern_1": {"type": "test_pattern", "features": {"type": "success", "duration": 1.6, "resources": {"cpu": 55.0, "memory": 520.0}}, "success_rate": 1.0, "frequency": 2, "last_seen": "2025-05-06T18:40:41.480323", "related_patterns": []}, "error_pattern_2": {"type": "error_pattern", "features": {"type": "error", "error_type": "timeout", "context": {"goal_id": "test_goal"}}, "success_rate": 0.0, "frequency": 1, "last_seen": "2025-05-06T18:40:41.483291", "related_patterns": []}, "performance_pattern_3": {"type": "performance_pattern", "features": {"type": "performance", "metrics": {"response_time": 2.5, "throughput": 100}}, "success_rate": 1.0, "frequency": 1, "last_seen": "2025-05-06T18:40:41.485237", "related_patterns": []}, "test_pattern_4": {"type": "test_pattern", "features": {"type": "test", "value": 42}, "success_rate": 1.0, "frequency": 4, "last_seen": "2025-05-06T18:40:41.493274", "related_patterns": []}, "execution_pattern_5": {"type": "execution_pattern", "features": {"goal_id": "test_goal", "success": true, "duration": 1.5, "resource_usage": {"cpu": 50.0, "memory": 512.0}, "error_type": null, "context": {"goal_id": "test_goal", "plugin_id": "test_plugin"}}, "success_rate": 1.0, "frequency": 1, "last_seen": "2025-05-06T18:40:41.495127", "related_patterns": []}, "execution_pattern_6": {"type": "execution_pattern", "features": {"goal_id": "test_goal", "success": false, "duration": 2.0, "resource_usage": {"cpu": 75.0, "memory": 768.0}, "error_type": "timeout", "context": {"goal_id": "test_goal", "plugin_id": "test_plugin"}}, "success_rate": 0.0, "frequency": 1, "last_seen": "2025-05-06T18:40:41.495722", "related_patterns": []}, "execution_pattern_7": {"type": "execution_pattern", "features": {"goal_id": "test_goal", "success": false, "duration": 1.0, "resource_usage": {"cpu": 50.0, "memory": 512.0}, "error_type": null, "context": {}}, "success_rate": 0.5065789473684211, "frequency": 152, "last_seen": "2025-05-06T18:40:41.798843", "related_patterns": []}, "execution_pattern_8": {"type": "execution_pattern", "features": {"goal_id": "test_goal", "success": false, "duration": 2.0, "resource_usage": {"cpu": 75.0, "memory": 768.0}, "error_type": "timeout", "context": {}}, "success_rate": 0.0, "frequency": 1, "last_seen": "2025-05-06T18:40:41.498236", "related_patterns": []}}, "adaptations": {"adapt_0": {"pattern_id": "error_pattern_2", "strategy": {"type": "parameter_adjustment", "parameters": {"timeout": 30, "retry_count": 3}}, "success_rate": 0.0, "last_applied": "2025-05-06T18:40:41.484025", "impact": 0.0}, "adapt_1": {"pattern_id": "performance_pattern_3", "strategy": {"type": "resource_allocation", "resources": {"cpu": 75.0, "memory": 1024.0}}, "success_rate": 0.0, "last_applied": "2025-05-06T18:40:41.486690", "impact": 0.0}, "adapt_2": {"pattern_id": "test_pattern_4", "strategy": {"type": "parameter_adjustment", "parameters": {"value": 43}}, "success_rate": 0.0, "last_applied": "2025-05-06T18:40:41.488891", "impact": 0.0}, "adapt_3": {"pattern_id": "test_pattern_4", "strategy": {"type": "parameter_adjustment", "parameters": {"value": 43}}, "success_rate": 0.0, "last_applied": "2025-05-06T18:40:41.493485", "impact": 0.0}, "adapt_4": {"pattern_id": "test_pattern_4", "strategy": {"type": "parameter_adjustment", "parameters": {"value": 43}}, "success_rate": 0.0, "last_applied": "2025-05-06T18:40:41.494335", "impact": 0.0}, "adapt_5": {"pattern_id": "test_pattern_4", "strategy": {"type": "parameter_adjustment", "parameters": {"value": 43}}, "success_rate": 0.0, "last_applied": "2025-05-06T18:40:41.494476", "impact": 0.0}, "adapt_6": {"pattern_id": "execution_pattern_6", "strategy": {"type": "parameter_adjustment", "parameters": {"timeout": 60, "retry_count": 4}}, "success_rate": 0.0, "last_applied": "2025-05-06T18:40:41.496063", "impact": 0.0}, "adapt_7": {"pattern_id": "execution_pattern_8", "strategy": {"type": "parameter_adjustment", "parameters": {"timeout": 60, "retry_count": 4}}, "success_rate": 0.0, "last_applied": "2025-05-06T18:40:41.498644", "impact": 0.0}, "adapt_8": {"pattern_id": "execution_pattern_7", "strategy": {"type": "error_handling", "parameters": {"retry_count": 3, "backoff_factor": 2.0}}, "success_rate": 0.0, "last_applied": "2025-05-06T18:40:41.503987", "impact": 0.0}, "adapt_9": {"pattern_id": "execution_pattern_7", "strategy": {"type": "error_handling", "parameters": {"retry_count": 3, "backoff_factor": 2.0}}, "success_rate": 0.0, "last_applied": "2025-05-06T18:40:41.505819", "impact": 0.0}, "adapt_10": {"pattern_id": "execution_pattern_7", "strategy": {"type": "error_handling", "parameters": {"retry_count": 3, "backoff_factor": 2.0}}, "success_rate": 0.0, "last_applied": "2025-05-06T18:40:41.507644", "impact": 0.0}, "adapt_11": {"pattern_id": "execution_pattern_7", "strategy": {"type": "error_handling", "parameters": {"retry_count": 3, "backoff_factor": 2.0}}, "success_rate": 0.0, "last_applied": "2025-05-06T18:40:41.509608", "impact": 0.0}, "adapt_12": {"pattern_id": "execution_pattern_7", "strategy": {"type": "error_handling", "parameters": {"retry_count": 3, "backoff_factor": 2.0}}, "success_rate": 0.0, "last_applied": "2025-05-06T18:40:41.511508", "impact": 0.0}, "adapt_13": {"pattern_id": "execution_pattern_7", "strategy": {"type": "error_handling", "parameters": {"retry_count": 3, "backoff_factor": 2.0}}, "success_rate": 0.0, "last_applied": "2025-05-06T18:40:41.513473", "impact": 0.0}, "adapt_14": {"pattern_id": "execution_pattern_7", "strategy": {"type": "error_handling", "parameters": {"retry_count": 3, "backoff_factor": 2.0}}, "success_rate": 0.0, "last_applied": "2025-05-06T18:40:41.515536", "impact": 0.0}, "adapt_15": {"pattern_id": "execution_pattern_7", "strategy": {"type": "error_handling", "parameters": {"retry_count": 3, "backoff_factor": 2.0}}, "success_rate": 0.0, "last_applied": "2025-05-06T18:40:41.517630", "impact": 0.0}, "adapt_16": {"pattern_id": "execution_pattern_7", "strategy": {"type": "error_handling", "parameters": {"retry_count": 3, "backoff_factor": 2.0}}, "success_rate": 0.0, "last_applied": "2025-05-06T18:40:41.519787", "impact": 0.0}, "adapt_17": {"pattern_id": "execution_pattern_7", "strategy": {"type": "error_handling", "parameters": {"retry_count": 3, "backoff_factor": 2.0}}, "success_rate": 0.0, "last_applied": "2025-05-06T18:40:41.522105", "impact": 0.0}, "adapt_18": {"pattern_id": "execution_pattern_7", "strategy": {"type": "error_handling", "parameters": {"retry_count": 3, "backoff_factor": 2.0}}, "success_rate": 0.0, "last_applied": "2025-05-06T18:40:41.524510", "impact": 0.0}, "adapt_19": {"pattern_id": "execution_pattern_7", "strategy": {"type": "error_handling", "parameters": {"retry_count": 3, "backoff_factor": 2.0}}, "success_rate": 0.0, "last_applied": "2025-05-06T18:40:41.526938", "impact": 0.0}, "adapt_20": {"pattern_id": "execution_pattern_7", "strategy": {"type": "error_handling", "parameters": {"retry_count": 3, "backoff_factor": 2.0}}, "success_rate": 0.0, "last_applied": "2025-05-06T18:40:41.529396", "impact": 0.0}, "adapt_21": {"pattern_id": "execution_pattern_7", "strategy": {"type": "error_handling", "parameters": {"retry_count": 3, "backoff_factor": 2.0}}, "success_rate": 0.0, "last_applied": "2025-05-06T18:40:41.531874", "impact": 0.0}, "adapt_22": {"pattern_id": "execution_pattern_7", "strategy": {"type": "error_handling", "parameters": {"retry_count": 3, "backoff_factor": 2.0}}, "success_rate": 0.0, "last_applied": "2025-05-06T18:40:41.534427", "impact": 0.0}, "adapt_23": {"pattern_id": "execution_pattern_7", "strategy": {"type": "error_handling", "parameters": {"retry_count": 3, "backoff_factor": 2.0}}, "success_rate": 0.0, "last_applied": "2025-05-06T18:40:41.537129", "impact": 0.0}, "adapt_24": {"pattern_id": "execution_pattern_7", "strategy": {"type": "error_handling", "parameters": {"retry_count": 3, "backoff_factor": 2.0}}, "success_rate": 0.0, "last_applied": "2025-05-06T18:40:41.539850", "impact": 0.0}, "adapt_25": {"pattern_id": "execution_pattern_7", "strategy": {"type": "error_handling", "parameters": {"retry_count": 3, "backoff_factor": 2.0}}, "success_rate": 0.0, "last_applied": "2025-05-06T18:40:41.542627", "impact": 0.0}, "adapt_26": {"pattern_id": "execution_pattern_7", "strategy": {"type": "error_handling", "parameters": {"retry_count": 3, "backoff_factor": 2.0}}, "success_rate": 0.0, "last_applied": "2025-05-06T18:40:41.545529", "impact": 0.0}, "adapt_27": {"pattern_id": "execution_pattern_7", "strategy": {"type": "error_handling", "parameters": {"retry_count": 3, "backoff_factor": 2.0}}, "success_rate": 0.0, "last_applied": "2025-05-06T18:40:41.548439", "impact": 0.0}, "adapt_28": {"pattern_id": "execution_pattern_7", "strategy": {"type": "error_handling", "parameters": {"retry_count": 3, "backoff_factor": 2.0}}, "success_rate": 0.0, "last_applied": "2025-05-06T18:40:41.551435", "impact": 0.0}, "adapt_29": {"pattern_id": "execution_pattern_7", "strategy": {"type": "error_handling", "parameters": {"retry_count": 3, "backoff_factor": 2.0}}, "success_rate": 0.0, "last_applied": "2025-05-06T18:40:41.554623", "impact": 0.0}, "adapt_30": {"pattern_id": "execution_pattern_7", "strategy": {"type": "error_handling", "parameters": {"retry_count": 3, "backoff_factor": 2.0}}, "success_rate": 0.0, "last_applied": "2025-05-06T18:40:41.557763", "impact": 0.0}, "adapt_31": {"pattern_id": "execution_pattern_7", "strategy": {"type": "error_handling", "parameters": {"retry_count": 3, "backoff_factor": 2.0}}, "success_rate": 0.0, "last_applied": "2025-05-06T18:40:41.561097", "impact": 0.0}, "adapt_32": {"pattern_id": "execution_pattern_7", "strategy": {"type": "error_handling", "parameters": {"retry_count": 3, "backoff_factor": 2.0}}, "success_rate": 0.0, "last_applied": "2025-05-06T18:40:41.564483", "impact": 0.0}, "adapt_33": {"pattern_id": "execution_pattern_7", "strategy": {"type": "error_handling", "parameters": {"retry_count": 3, "backoff_factor": 2.0}}, "success_rate": 0.0, "last_applied": "2025-05-06T18:40:41.567871", "impact": 0.0}, "adapt_34": {"pattern_id": "execution_pattern_7", "strategy": {"type": "error_handling", "parameters": {"retry_count": 3, "backoff_factor": 2.0}}, "success_rate": 0.0, "last_applied": "2025-05-06T18:40:41.571396", "impact": 0.0}, "adapt_35": {"pattern_id": "execution_pattern_7", "strategy": {"type": "error_handling", "parameters": {"retry_count": 3, "backoff_factor": 2.0}}, "success_rate": 0.0, "last_applied": "2025-05-06T18:40:41.575107", "impact": 0.0}, "adapt_36": {"pattern_id": "execution_pattern_7", "strategy": {"type": "error_handling", "parameters": {"retry_count": 3, "backoff_factor": 2.0}}, "success_rate": 0.0, "last_applied": "2025-05-06T18:40:41.578687", "impact": 0.0}, "adapt_37": {"pattern_id": "execution_pattern_7", "strategy": {"type": "error_handling", "parameters": {"retry_count": 3, "backoff_factor": 2.0}}, "success_rate": 0.0, "last_applied": "2025-05-06T18:40:41.582309", "impact": 0.0}, "adapt_38": {"pattern_id": "execution_pattern_7", "strategy": {"type": "error_handling", "parameters": {"retry_count": 3, "backoff_factor": 2.0}}, "success_rate": 0.0, "last_applied": "2025-05-06T18:40:41.586098", "impact": 0.0}, "adapt_39": {"pattern_id": "execution_pattern_7", "strategy": {"type": "error_handling", "parameters": {"retry_count": 3, "backoff_factor": 2.0}}, "success_rate": 0.0, "last_applied": "2025-05-06T18:40:41.589982", "impact": 0.0}, "adapt_40": {"pattern_id": "execution_pattern_7", "strategy": {"type": "error_handling", "parameters": {"retry_count": 3, "backoff_factor": 2.0}}, "success_rate": 0.0, "last_applied": "2025-05-06T18:40:41.593796", "impact": 0.0}, "adapt_41": {"pattern_id": "execution_pattern_7", "strategy": {"type": "error_handling", "parameters": {"retry_count": 3, "backoff_factor": 2.0}}, "success_rate": 0.0, "last_applied": "2025-05-06T18:40:41.597715", "impact": 0.0}, "adapt_42": {"pattern_id": "execution_pattern_7", "strategy": {"type": "error_handling", "parameters": {"retry_count": 3, "backoff_factor": 2.0}}, "success_rate": 0.0, "last_applied": "2025-05-06T18:40:41.601647", "impact": 0.0}, "adapt_43": {"pattern_id": "execution_pattern_7", "strategy": {"type": "error_handling", "parameters": {"retry_count": 3, "backoff_factor": 2.0}}, "success_rate": 0.0, "last_applied": "2025-05-06T18:40:41.605811", "impact": 0.0}, "adapt_44": {"pattern_id": "execution_pattern_7", "strategy": {"type": "error_handling", "parameters": {"retry_count": 3, "backoff_factor": 2.0}}, "success_rate": 0.0, "last_applied": "2025-05-06T18:40:41.609975", "impact": 0.0}, "adapt_45": {"pattern_id": "execution_pattern_7", "strategy": {"type": "error_handling", "parameters": {"retry_count": 3, "backoff_factor": 2.0}}, "success_rate": 0.0, "last_applied": "2025-05-06T18:40:41.614098", "impact": 0.0}, "adapt_46": {"pattern_id": "execution_pattern_7", "strategy": {"type": "error_handling", "parameters": {"retry_count": 3, "backoff_factor": 2.0}}, "success_rate": 0.0, "last_applied": "2025-05-06T18:40:41.618281", "impact": 0.0}, "adapt_47": {"pattern_id": "execution_pattern_7", "strategy": {"type": "error_handling", "parameters": {"retry_count": 3, "backoff_factor": 2.0}}, "success_rate": 0.0, "last_applied": "2025-05-06T18:40:41.622616", "impact": 0.0}, "adapt_48": {"pattern_id": "execution_pattern_7", "strategy": {"type": "error_handling", "parameters": {"retry_count": 3, "backoff_factor": 2.0}}, "success_rate": 0.0, "last_applied": "2025-05-06T18:40:41.626915", "impact": 0.0}, "adapt_49": {"pattern_id": "execution_pattern_7", "strategy": {"type": "error_handling", "parameters": {"retry_count": 3, "backoff_factor": 2.0}}, "success_rate": 0.0, "last_applied": "2025-05-06T18:40:41.631331", "impact": 0.0}, "adapt_50": {"pattern_id": "execution_pattern_7", "strategy": {"type": "error_handling", "parameters": {"retry_count": 3, "backoff_factor": 2.0}}, "success_rate": 0.0, "last_applied": "2025-05-06T18:40:41.635825", "impact": 0.0}, "adapt_51": {"pattern_id": "execution_pattern_7", "strategy": {"type": "error_handling", "parameters": {"retry_count": 3, "backoff_factor": 2.0}}, "success_rate": 0.0, "last_applied": "2025-05-06T18:40:41.640365", "impact": 0.0}, "adapt_52": {"pattern_id": "execution_pattern_7", "strategy": {"type": "error_handling", "parameters": {"retry_count": 3, "backoff_factor": 2.0}}, "success_rate": 0.0, "last_applied": "2025-05-06T18:40:41.644949", "impact": 0.0}, "adapt_53": {"pattern_id": "execution_pattern_7", "strategy": {"type": "error_handling", "parameters": {"retry_count": 3, "backoff_factor": 2.0}}, "success_rate": 0.0, "last_applied": "2025-05-06T18:40:41.649591", "impact": 0.0}, "adapt_54": {"pattern_id": "execution_pattern_7", "strategy": {"type": "error_handling", "parameters": {"retry_count": 3, "backoff_factor": 2.0}}, "success_rate": 0.0, "last_applied": "2025-05-06T18:40:41.654340", "impact": 0.0}, "adapt_55": {"pattern_id": "execution_pattern_7", "strategy": {"type": "error_handling", "parameters": {"retry_count": 3, "backoff_factor": 2.0}}, "success_rate": 0.0, "last_applied": "2025-05-06T18:40:41.659100", "impact": 0.0}, "adapt_56": {"pattern_id": "execution_pattern_7", "strategy": {"type": "error_handling", "parameters": {"retry_count": 3, "backoff_factor": 2.0}}, "success_rate": 0.0, "last_applied": "2025-05-06T18:40:41.663931", "impact": 0.0}, "adapt_57": {"pattern_id": "execution_pattern_7", "strategy": {"type": "error_handling", "parameters": {"retry_count": 3, "backoff_factor": 2.0}}, "success_rate": 0.0, "last_applied": "2025-05-06T18:40:41.668810", "impact": 0.0}, "adapt_58": {"pattern_id": "execution_pattern_7", "strategy": {"type": "error_handling", "parameters": {"retry_count": 3, "backoff_factor": 2.0}}, "success_rate": 0.0, "last_applied": "2025-05-06T18:40:41.673834", "impact": 0.0}, "adapt_59": {"pattern_id": "execution_pattern_7", "strategy": {"type": "error_handling", "parameters": {"retry_count": 3, "backoff_factor": 2.0}}, "success_rate": 0.0, "last_applied": "2025-05-06T18:40:41.679083", "impact": 0.0}, "adapt_60": {"pattern_id": "execution_pattern_7", "strategy": {"type": "error_handling", "parameters": {"retry_count": 3, "backoff_factor": 2.0}}, "success_rate": 0.0, "last_applied": "2025-05-06T18:40:41.684027", "impact": 0.0}, "adapt_61": {"pattern_id": "execution_pattern_7", "strategy": {"type": "error_handling", "parameters": {"retry_count": 3, "backoff_factor": 2.0}}, "success_rate": 0.0, "last_applied": "2025-05-06T18:40:41.689095", "impact": 0.0}, "adapt_62": {"pattern_id": "execution_pattern_7", "strategy": {"type": "error_handling", "parameters": {"retry_count": 3, "backoff_factor": 2.0}}, "success_rate": 0.0, "last_applied": "2025-05-06T18:40:41.694082", "impact": 0.0}, "adapt_63": {"pattern_id": "execution_pattern_7", "strategy": {"type": "error_handling", "parameters": {"retry_count": 3, "backoff_factor": 2.0}}, "success_rate": 0.0, "last_applied": "2025-05-06T18:40:41.699144", "impact": 0.0}, "adapt_64": {"pattern_id": "execution_pattern_7", "strategy": {"type": "error_handling", "parameters": {"retry_count": 3, "backoff_factor": 2.0}}, "success_rate": 0.0, "last_applied": "2025-05-06T18:40:41.704253", "impact": 0.0}, "adapt_65": {"pattern_id": "execution_pattern_7", "strategy": {"type": "error_handling", "parameters": {"retry_count": 3, "backoff_factor": 2.0}}, "success_rate": 0.0, "last_applied": "2025-05-06T18:40:41.709312", "impact": 0.0}, "adapt_66": {"pattern_id": "execution_pattern_7", "strategy": {"type": "error_handling", "parameters": {"retry_count": 3, "backoff_factor": 2.0}}, "success_rate": 0.0, "last_applied": "2025-05-06T18:40:41.714431", "impact": 0.0}, "adapt_67": {"pattern_id": "execution_pattern_7", "strategy": {"type": "error_handling", "parameters": {"retry_count": 3, "backoff_factor": 2.0}}, "success_rate": 0.0, "last_applied": "2025-05-06T18:40:41.719614", "impact": 0.0}, "adapt_68": {"pattern_id": "execution_pattern_7", "strategy": {"type": "error_handling", "parameters": {"retry_count": 3, "backoff_factor": 2.0}}, "success_rate": 0.0, "last_applied": "2025-05-06T18:40:41.724795", "impact": 0.0}, "adapt_69": {"pattern_id": "execution_pattern_7", "strategy": {"type": "error_handling", "parameters": {"retry_count": 3, "backoff_factor": 2.0}}, "success_rate": 0.0, "last_applied": "2025-05-06T18:40:41.730002", "impact": 0.0}, "adapt_70": {"pattern_id": "execution_pattern_7", "strategy": {"type": "error_handling", "parameters": {"retry_count": 3, "backoff_factor": 2.0}}, "success_rate": 0.0, "last_applied": "2025-05-06T18:40:41.735174", "impact": 0.0}, "adapt_71": {"pattern_id": "execution_pattern_7", "strategy": {"type": "error_handling", "parameters": {"retry_count": 3, "backoff_factor": 2.0}}, "success_rate": 0.0, "last_applied": "2025-05-06T18:40:41.740420", "impact": 0.0}, "adapt_72": {"pattern_id": "execution_pattern_7", "strategy": {"type": "error_handling", "parameters": {"retry_count": 3, "backoff_factor": 2.0}}, "success_rate": 0.0, "last_applied": "2025-05-06T18:40:41.745665", "impact": 0.0}, "adapt_73": {"pattern_id": "execution_pattern_7", "strategy": {"type": "error_handling", "parameters": {"retry_count": 3, "backoff_factor": 2.0}}, "success_rate": 0.0, "last_applied": "2025-05-06T18:40:41.750942", "impact": 0.0}, "adapt_74": {"pattern_id": "execution_pattern_7", "strategy": {"type": "error_handling", "parameters": {"retry_count": 3, "backoff_factor": 2.0}}, "success_rate": 0.0, "last_applied": "2025-05-06T18:40:41.756262", "impact": 0.0}, "adapt_75": {"pattern_id": "execution_pattern_7", "strategy": {"type": "error_handling", "parameters": {"retry_count": 3, "backoff_factor": 2.0}}, "success_rate": 0.0, "last_applied": "2025-05-06T18:40:41.761503", "impact": 0.0}, "adapt_76": {"pattern_id": "execution_pattern_7", "strategy": {"type": "error_handling", "parameters": {"retry_count": 3, "backoff_factor": 2.0}}, "success_rate": 0.0, "last_applied": "2025-05-06T18:40:41.766843", "impact": 0.0}, "adapt_77": {"pattern_id": "execution_pattern_7", "strategy": {"type": "error_handling", "parameters": {"retry_count": 3, "backoff_factor": 2.0}}, "success_rate": 0.0, "last_applied": "2025-05-06T18:40:41.772421", "impact": 0.0}, "adapt_78": {"pattern_id": "execution_pattern_7", "strategy": {"type": "error_handling", "parameters": {"retry_count": 3, "backoff_factor": 2.0}}, "success_rate": 0.0, "last_applied": "2025-05-06T18:40:41.777864", "impact": 0.0}, "adapt_79": {"pattern_id": "execution_pattern_7", "strategy": {"type": "error_handling", "parameters": {"retry_count": 3, "backoff_factor": 2.0}}, "success_rate": 0.0, "last_applied": "2025-05-06T18:40:41.783301", "impact": 0.0}, "adapt_80": {"pattern_id": "execution_pattern_7", "strategy": {"type": "error_handling", "parameters": {"retry_count": 3, "backoff_factor": 2.0}}, "success_rate": 0.0, "last_applied": "2025-05-06T18:40:41.788830", "impact": 0.0}, "adapt_81": {"pattern_id": "execution_pattern_7", "strategy": {"type": "error_handling", "parameters": {"retry_count": 3, "backoff_factor": 2.0}}, "success_rate": 0.0, "last_applied": "2025-05-06T18:40:41.794451", "impact": 0.0}, "adapt_82": {"pattern_id": "execution_pattern_7", "strategy": {"type": "error_handling", "parameters": {"retry_count": 3, "backoff_factor": 2.0}}, "success_rate": 0.0, "last_applied": "2025-05-06T18:40:41.799945", "impact": 0.0}}, "pattern_similarities": {"test_pattern_0": {"test_pattern_1": 0.0, "error_pattern_2": 0.0, "performance_pattern_3": 0.0, "test_pattern_4": 0.0, "execution_pattern_5": 0.0, "execution_pattern_6": 0.0, "execution_pattern_7": 0.0, "execution_pattern_8": 0.09775201108053398}, "test_pattern_1": {"test_pattern_0": 0.0, "error_pattern_2": 0.0, "performance_pattern_3": 0.0, "test_pattern_4": 0.0, "execution_pattern_5": 0.0, "execution_pattern_6": 0.0, "execution_pattern_7": 0.0, "execution_pattern_8": 0.0}, "error_pattern_2": {"test_pattern_0": 0.0, "test_pattern_1": 0.0, "performance_pattern_3": 0.40505119454169436, "test_pattern_4": 0.0, "execution_pattern_5": 0.0, "execution_pattern_6": 0.0, "execution_pattern_7": 0.0, "execution_pattern_8": 0.0}, "performance_pattern_3": {"test_pattern_0": 0.0, "test_pattern_1": 0.0, "error_pattern_2": 0.40505119454169436, "test_pattern_4": 0.0, "execution_pattern_5": 0.0, "execution_pattern_6": 0.0, "execution_pattern_7": 0.0, "execution_pattern_8": 0.0}, "test_pattern_4": {"test_pattern_0": 0.0, "test_pattern_1": 0.0, "error_pattern_2": 0.0, "performance_pattern_3": 0.0, "execution_pattern_5": 0.0, "execution_pattern_6": 0.0, "execution_pattern_7": 0.0, "execution_pattern_8": 0.0}, "execution_pattern_5": {"test_pattern_0": 0.0, "test_pattern_1": 0.0, "error_pattern_2": 0.0, "performance_pattern_3": 0.0, "test_pattern_4": 0.0, "execution_pattern_6": 0.0, "execution_pattern_7": 0.0, "execution_pattern_8": 0.0}, "execution_pattern_6": {"test_pattern_0": 0.0, "test_pattern_1": 0.0, "error_pattern_2": 0.0, "performance_pattern_3": 0.0, "test_pattern_4": 0.0, "execution_pattern_5": 0.0, "execution_pattern_7": 0.0, "execution_pattern_8": 0.0}, "execution_pattern_7": {"test_pattern_0": 0.0, "test_pattern_1": 0.0, "error_pattern_2": 0.0, "performance_pattern_3": 0.0, "test_pattern_4": 0.0, "execution_pattern_5": 0.0, "execution_pattern_6": 0.0, "execution_pattern_8": 0.0}, "execution_pattern_8": {"test_pattern_0": 0.09775201108053398, "test_pattern_1": 0.0, "error_pattern_2": 0.0, "performance_pattern_3": 0.0, "test_pattern_4": 0.0, "execution_pattern_5": 0.0, "execution_pattern_6": 0.0, "execution_pattern_7": 0.0}}, "learning_data": {"test_goal": {"executions": [{"timestamp": "2025-05-06T18:40:41.566474", "result": {"success": true, "duration": 1.0, "resource_usage": {"cpu": 50.0, "memory": 512.0}}}, {"timestamp": "2025-05-06T18:40:41.568475", "result": {"success": false, "duration": 1.0, "resource_usage": {"cpu": 50.0, "memory": 512.0}}}, {"timestamp": "2025-05-06T18:40:41.569957", "result": {"success": true, "duration": 1.0, "resource_usage": {"cpu": 50.0, "memory": 512.0}}}, {"timestamp": "2025-05-06T18:40:41.572184", "result": {"success": false, "duration": 1.0, "resource_usage": {"cpu": 50.0, "memory": 512.0}}}, {"timestamp": "2025-05-06T18:40:41.573642", "result": {"success": true, "duration": 1.0, "resource_usage": {"cpu": 50.0, "memory": 512.0}}}, {"timestamp": "2025-05-06T18:40:41.575730", "result": {"success": false, "duration": 1.0, "resource_usage": {"cpu": 50.0, "memory": 512.0}}}, {"timestamp": "2025-05-06T18:40:41.577199", "result": {"success": true, "duration": 1.0, "resource_usage": {"cpu": 50.0, "memory": 512.0}}}, {"timestamp": "2025-05-06T18:40:41.579326", "result": {"success": false, "duration": 1.0, "resource_usage": {"cpu": 50.0, "memory": 512.0}}}, {"timestamp": "2025-05-06T18:40:41.580816", "result": {"success": true, "duration": 1.0, "resource_usage": {"cpu": 50.0, "memory": 512.0}}}, {"timestamp": "2025-05-06T18:40:41.582961", "result": {"success": false, "duration": 1.0, "resource_usage": {"cpu": 50.0, "memory": 512.0}}}, {"timestamp": "2025-05-06T18:40:41.584518", "result": {"success": true, "duration": 1.0, "resource_usage": {"cpu": 50.0, "memory": 512.0}}}, {"timestamp": "2025-05-06T18:40:41.586829", "result": {"success": false, "duration": 1.0, "resource_usage": {"cpu": 50.0, "memory": 512.0}}}, {"timestamp": "2025-05-06T18:40:41.588420", "result": {"success": true, "duration": 1.0, "resource_usage": {"cpu": 50.0, "memory": 512.0}}}, {"timestamp": "2025-05-06T18:40:41.590661", "result": {"success": false, "duration": 1.0, "resource_usage": {"cpu": 50.0, "memory": 512.0}}}, {"timestamp": "2025-05-06T18:40:41.592226", "result": {"success": true, "duration": 1.0, "resource_usage": {"cpu": 50.0, "memory": 512.0}}}, {"timestamp": "2025-05-06T18:40:41.594477", "result": {"success": false, "duration": 1.0, "resource_usage": {"cpu": 50.0, "memory": 512.0}}}, {"timestamp": "2025-05-06T18:40:41.596134", "result": {"success": true, "duration": 1.0, "resource_usage": {"cpu": 50.0, "memory": 512.0}}}, {"timestamp": "2025-05-06T18:40:41.598416", "result": {"success": false, "duration": 1.0, "resource_usage": {"cpu": 50.0, "memory": 512.0}}}, {"timestamp": "2025-05-06T18:40:41.600034", "result": {"success": true, "duration": 1.0, "resource_usage": {"cpu": 50.0, "memory": 512.0}}}, {"timestamp": "2025-05-06T18:40:41.602359", "result": {"success": false, "duration": 1.0, "resource_usage": {"cpu": 50.0, "memory": 512.0}}}, {"timestamp": "2025-05-06T18:40:41.604101", "result": {"success": true, "duration": 1.0, "resource_usage": {"cpu": 50.0, "memory": 512.0}}}, {"timestamp": "2025-05-06T18:40:41.606561", "result": {"success": false, "duration": 1.0, "resource_usage": {"cpu": 50.0, "memory": 512.0}}}, {"timestamp": "2025-05-06T18:40:41.608268", "result": {"success": true, "duration": 1.0, "resource_usage": {"cpu": 50.0, "memory": 512.0}}}, {"timestamp": "2025-05-06T18:40:41.610723", "result": {"success": false, "duration": 1.0, "resource_usage": {"cpu": 50.0, "memory": 512.0}}}, {"timestamp": "2025-05-06T18:40:41.612424", "result": {"success": true, "duration": 1.0, "resource_usage": {"cpu": 50.0, "memory": 512.0}}}, {"timestamp": "2025-05-06T18:40:41.614844", "result": {"success": false, "duration": 1.0, "resource_usage": {"cpu": 50.0, "memory": 512.0}}}, {"timestamp": "2025-05-06T18:40:41.616562", "result": {"success": true, "duration": 1.0, "resource_usage": {"cpu": 50.0, "memory": 512.0}}}, {"timestamp": "2025-05-06T18:40:41.619086", "result": {"success": false, "duration": 1.0, "resource_usage": {"cpu": 50.0, "memory": 512.0}}}, {"timestamp": "2025-05-06T18:40:41.620842", "result": {"success": true, "duration": 1.0, "resource_usage": {"cpu": 50.0, "memory": 512.0}}}, {"timestamp": "2025-05-06T18:40:41.623386", "result": {"success": false, "duration": 1.0, "resource_usage": {"cpu": 50.0, "memory": 512.0}}}, {"timestamp": "2025-05-06T18:40:41.625142", "result": {"success": true, "duration": 1.0, "resource_usage": {"cpu": 50.0, "memory": 512.0}}}, {"timestamp": "2025-05-06T18:40:41.627697", "result": {"success": false, "duration": 1.0, "resource_usage": {"cpu": 50.0, "memory": 512.0}}}, {"timestamp": "2025-05-06T18:40:41.629535", "result": {"success": true, "duration": 1.0, "resource_usage": {"cpu": 50.0, "memory": 512.0}}}, {"timestamp": "2025-05-06T18:40:41.632140", "result": {"success": false, "duration": 1.0, "resource_usage": {"cpu": 50.0, "memory": 512.0}}}, {"timestamp": "2025-05-06T18:40:41.633952", "result": {"success": true, "duration": 1.0, "resource_usage": {"cpu": 50.0, "memory": 512.0}}}, {"timestamp": "2025-05-06T18:40:41.636672", "result": {"success": false, "duration": 1.0, "resource_usage": {"cpu": 50.0, "memory": 512.0}}}, {"timestamp": "2025-05-06T18:40:41.638512", "result": {"success": true, "duration": 1.0, "resource_usage": {"cpu": 50.0, "memory": 512.0}}}, {"timestamp": "2025-05-06T18:40:41.641191", "result": {"success": false, "duration": 1.0, "resource_usage": {"cpu": 50.0, "memory": 512.0}}}, {"timestamp": "2025-05-06T18:40:41.643053", "result": {"success": true, "duration": 1.0, "resource_usage": {"cpu": 50.0, "memory": 512.0}}}, {"timestamp": "2025-05-06T18:40:41.645786", "result": {"success": false, "duration": 1.0, "resource_usage": {"cpu": 50.0, "memory": 512.0}}}, {"timestamp": "2025-05-06T18:40:41.647668", "result": {"success": true, "duration": 1.0, "resource_usage": {"cpu": 50.0, "memory": 512.0}}}, {"timestamp": "2025-05-06T18:40:41.650448", "result": {"success": false, "duration": 1.0, "resource_usage": {"cpu": 50.0, "memory": 512.0}}}, {"timestamp": "2025-05-06T18:40:41.652358", "result": {"success": true, "duration": 1.0, "resource_usage": {"cpu": 50.0, "memory": 512.0}}}, {"timestamp": "2025-05-06T18:40:41.655208", "result": {"success": false, "duration": 1.0, "resource_usage": {"cpu": 50.0, "memory": 512.0}}}, {"timestamp": "2025-05-06T18:40:41.657143", "result": {"success": true, "duration": 1.0, "resource_usage": {"cpu": 50.0, "memory": 512.0}}}, {"timestamp": "2025-05-06T18:40:41.659987", "result": {"success": false, "duration": 1.0, "resource_usage": {"cpu": 50.0, "memory": 512.0}}}, {"timestamp": "2025-05-06T18:40:41.661956", "result": {"success": true, "duration": 1.0, "resource_usage": {"cpu": 50.0, "memory": 512.0}}}, {"timestamp": "2025-05-06T18:40:41.664843", "result": {"success": false, "duration": 1.0, "resource_usage": {"cpu": 50.0, "memory": 512.0}}}, {"timestamp": "2025-05-06T18:40:41.666840", "result": {"success": true, "duration": 1.0, "resource_usage": {"cpu": 50.0, "memory": 512.0}}}, {"timestamp": "2025-05-06T18:40:41.669792", "result": {"success": false, "duration": 1.0, "resource_usage": {"cpu": 50.0, "memory": 512.0}}}, {"timestamp": "2025-05-06T18:40:41.671831", "result": {"success": true, "duration": 1.0, "resource_usage": {"cpu": 50.0, "memory": 512.0}}}, {"timestamp": "2025-05-06T18:40:41.674737", "result": {"success": false, "duration": 1.0, "resource_usage": {"cpu": 50.0, "memory": 512.0}}}, {"timestamp": "2025-05-06T18:40:41.676762", "result": {"success": true, "duration": 1.0, "resource_usage": {"cpu": 50.0, "memory": 512.0}}}, {"timestamp": "2025-05-06T18:40:41.679981", "result": {"success": false, "duration": 1.0, "resource_usage": {"cpu": 50.0, "memory": 512.0}}}, {"timestamp": "2025-05-06T18:40:41.682028", "result": {"success": true, "duration": 1.0, "resource_usage": {"cpu": 50.0, "memory": 512.0}}}, {"timestamp": "2025-05-06T18:40:41.684935", "result": {"success": false, "duration": 1.0, "resource_usage": {"cpu": 50.0, "memory": 512.0}}}, {"timestamp": "2025-05-06T18:40:41.687027", "result": {"success": true, "duration": 1.0, "resource_usage": {"cpu": 50.0, "memory": 512.0}}}, {"timestamp": "2025-05-06T18:40:41.690006", "result": {"success": false, "duration": 1.0, "resource_usage": {"cpu": 50.0, "memory": 512.0}}}, {"timestamp": "2025-05-06T18:40:41.692033", "result": {"success": true, "duration": 1.0, "resource_usage": {"cpu": 50.0, "memory": 512.0}}}, {"timestamp": "2025-05-06T18:40:41.695007", "result": {"success": false, "duration": 1.0, "resource_usage": {"cpu": 50.0, "memory": 512.0}}}, {"timestamp": "2025-05-06T18:40:41.697094", "result": {"success": true, "duration": 1.0, "resource_usage": {"cpu": 50.0, "memory": 512.0}}}, {"timestamp": "2025-05-06T18:40:41.700058", "result": {"success": false, "duration": 1.0, "resource_usage": {"cpu": 50.0, "memory": 512.0}}}, {"timestamp": "2025-05-06T18:40:41.702100", "result": {"success": true, "duration": 1.0, "resource_usage": {"cpu": 50.0, "memory": 512.0}}}, {"timestamp": "2025-05-06T18:40:41.705196", "result": {"success": false, "duration": 1.0, "resource_usage": {"cpu": 50.0, "memory": 512.0}}}, {"timestamp": "2025-05-06T18:40:41.707245", "result": {"success": true, "duration": 1.0, "resource_usage": {"cpu": 50.0, "memory": 512.0}}}, {"timestamp": "2025-05-06T18:40:41.710261", "result": {"success": false, "duration": 1.0, "resource_usage": {"cpu": 50.0, "memory": 512.0}}}, {"timestamp": "2025-05-06T18:40:41.712351", "result": {"success": true, "duration": 1.0, "resource_usage": {"cpu": 50.0, "memory": 512.0}}}, {"timestamp": "2025-05-06T18:40:41.715359", "result": {"success": false, "duration": 1.0, "resource_usage": {"cpu": 50.0, "memory": 512.0}}}, {"timestamp": "2025-05-06T18:40:41.717417", "result": {"success": true, "duration": 1.0, "resource_usage": {"cpu": 50.0, "memory": 512.0}}}, {"timestamp": "2025-05-06T18:40:41.720603", "result": {"success": false, "duration": 1.0, "resource_usage": {"cpu": 50.0, "memory": 512.0}}}, {"timestamp": "2025-05-06T18:40:41.722710", "result": {"success": true, "duration": 1.0, "resource_usage": {"cpu": 50.0, "memory": 512.0}}}, {"timestamp": "2025-05-06T18:40:41.725738", "result": {"success": false, "duration": 1.0, "resource_usage": {"cpu": 50.0, "memory": 512.0}}}, {"timestamp": "2025-05-06T18:40:41.727844", "result": {"success": true, "duration": 1.0, "resource_usage": {"cpu": 50.0, "memory": 512.0}}}, {"timestamp": "2025-05-06T18:40:41.730975", "result": {"success": false, "duration": 1.0, "resource_usage": {"cpu": 50.0, "memory": 512.0}}}, {"timestamp": "2025-05-06T18:40:41.733080", "result": {"success": true, "duration": 1.0, "resource_usage": {"cpu": 50.0, "memory": 512.0}}}, {"timestamp": "2025-05-06T18:40:41.736168", "result": {"success": false, "duration": 1.0, "resource_usage": {"cpu": 50.0, "memory": 512.0}}}, {"timestamp": "2025-05-06T18:40:41.738321", "result": {"success": true, "duration": 1.0, "resource_usage": {"cpu": 50.0, "memory": 512.0}}}, {"timestamp": "2025-05-06T18:40:41.741375", "result": {"success": false, "duration": 1.0, "resource_usage": {"cpu": 50.0, "memory": 512.0}}}, {"timestamp": "2025-05-06T18:40:41.743524", "result": {"success": true, "duration": 1.0, "resource_usage": {"cpu": 50.0, "memory": 512.0}}}, {"timestamp": "2025-05-06T18:40:41.746733", "result": {"success": false, "duration": 1.0, "resource_usage": {"cpu": 50.0, "memory": 512.0}}}, {"timestamp": "2025-05-06T18:40:41.748845", "result": {"success": true, "duration": 1.0, "resource_usage": {"cpu": 50.0, "memory": 512.0}}}, {"timestamp": "2025-05-06T18:40:41.751903", "result": {"success": false, "duration": 1.0, "resource_usage": {"cpu": 50.0, "memory": 512.0}}}, {"timestamp": "2025-05-06T18:40:41.754114", "result": {"success": true, "duration": 1.0, "resource_usage": {"cpu": 50.0, "memory": 512.0}}}, {"timestamp": "2025-05-06T18:40:41.757227", "result": {"success": false, "duration": 1.0, "resource_usage": {"cpu": 50.0, "memory": 512.0}}}, {"timestamp": "2025-05-06T18:40:41.759353", "result": {"success": true, "duration": 1.0, "resource_usage": {"cpu": 50.0, "memory": 512.0}}}, {"timestamp": "2025-05-06T18:40:41.762500", "result": {"success": false, "duration": 1.0, "resource_usage": {"cpu": 50.0, "memory": 512.0}}}, {"timestamp": "2025-05-06T18:40:41.764666", "result": {"success": true, "duration": 1.0, "resource_usage": {"cpu": 50.0, "memory": 512.0}}}, {"timestamp": "2025-05-06T18:40:41.767821", "result": {"success": false, "duration": 1.0, "resource_usage": {"cpu": 50.0, "memory": 512.0}}}, {"timestamp": "2025-05-06T18:40:41.770092", "result": {"success": true, "duration": 1.0, "resource_usage": {"cpu": 50.0, "memory": 512.0}}}, {"timestamp": "2025-05-06T18:40:41.773434", "result": {"success": false, "duration": 1.0, "resource_usage": {"cpu": 50.0, "memory": 512.0}}}, {"timestamp": "2025-05-06T18:40:41.775640", "result": {"success": true, "duration": 1.0, "resource_usage": {"cpu": 50.0, "memory": 512.0}}}, {"timestamp": "2025-05-06T18:40:41.778865", "result": {"success": false, "duration": 1.0, "resource_usage": {"cpu": 50.0, "memory": 512.0}}}, {"timestamp": "2025-05-06T18:40:41.781115", "result": {"success": true, "duration": 1.0, "resource_usage": {"cpu": 50.0, "memory": 512.0}}}, {"timestamp": "2025-05-06T18:40:41.784294", "result": {"success": false, "duration": 1.0, "resource_usage": {"cpu": 50.0, "memory": 512.0}}}, {"timestamp": "2025-05-06T18:40:41.786601", "result": {"success": true, "duration": 1.0, "resource_usage": {"cpu": 50.0, "memory": 512.0}}}, {"timestamp": "2025-05-06T18:40:41.789829", "result": {"success": false, "duration": 1.0, "resource_usage": {"cpu": 50.0, "memory": 512.0}}}, {"timestamp": "2025-05-06T18:40:41.792254", "result": {"success": true, "duration": 1.0, "resource_usage": {"cpu": 50.0, "memory": 512.0}}}, {"timestamp": "2025-05-06T18:40:41.795481", "result": {"success": false, "duration": 1.0, "resource_usage": {"cpu": 50.0, "memory": 512.0}}}, {"timestamp": "2025-05-06T18:40:41.797685", "result": {"success": true, "duration": 1.0, "resource_usage": {"cpu": 50.0, "memory": 512.0}}}, {"timestamp": "2025-05-06T18:40:41.800949", "result": {"success": false, "duration": 1.0, "resource_usage": {"cpu": 50.0, "memory": 512.0}}}], "success_rate": 0.5032258064516132, "total_executions": 155, "resource_usage": {"cpu": [50.0, 50.0, 50.0, 50.0, 50.0, 50.0, 50.0, 50.0, 50.0, 50.0, 50.0, 50.0, 50.0, 50.0, 50.0, 50.0, 50.0, 50.0, 50.0, 50.0, 50.0, 50.0, 50.0, 50.0, 50.0, 50.0, 50.0, 50.0, 50.0, 50.0, 50.0, 50.0, 50.0, 50.0, 50.0, 50.0, 50.0, 50.0, 50.0, 50.0, 50.0, 50.0, 50.0, 50.0, 50.0, 50.0, 50.0, 50.0, 50.0, 50.0], "memory": [512.0, 512.0, 512.0, 512.0, 512.0, 512.0, 512.0, 512.0, 512.0, 512.0, 512.0, 512.0, 512.0, 512.0, 512.0, 512.0, 512.0, 512.0, 512.0, 512.0, 512.0, 512.0, 512.0, 512.0, 512.0, 512.0, 512.0, 512.0, 512.0, 512.0, 512.0, 512.0, 512.0, 512.0, 512.0, 512.0, 512.0, 512.0, 512.0, 512.0, 512.0, 512.0, 512.0, 512.0, 512.0, 512.0, 512.0, 512.0, 512.0, 512.0]}, "error_types": {"timeout": 2}}}}